datasette_bplist/__init__.py
datasette_bplist-0.1.dist-info/LICENSE
datasette_bplist-0.1.dist-info/METADATA
datasette_bplist-0.1.dist-info/WHEEL
datasette_bplist-0.1.dist-info/entry_points.txt
datasette_bplist-0.1.dist-info/top_level.txt
datasette_bplist-0.1.dist-info/RECORD
