Metadata-Version: 2.1
Name: datasette-bplist
Version: 0.1
Summary: Datasette plugin for working with Apple's binary plist format
Home-page: https://github.com/simonw/datasette-bplist
Author: Simon Willison
License: Apache License, Version 2.0
Platform: UNKNOWN
Requires-Dist: datasette
Requires-Dist: bpylist
Provides-Extra: test
Requires-Dist: pytest ; extra == 'test'
